Ayla/__init__.py
Ayla/cards/__init__.py
Ayla/cards/assets/__init__.py
Ayla/cards/assets/curveborder.png
Ayla/cards/assets/curvedoverlay.png
Ayla/cards/assets/fonts/__init__.py
Ayla/cards/assets/fonts/juice.otf
Ayla/cards/assets/fonts/levelfont.otf
Ayla/cards/assets/fonts/poppins.ttf
Ayla/cards/assets/fonts/rabbit.ttf
Ayla/cards/assets/mask_circle.jpg
Ayla/cards/assets/overlay1.png
Ayla/cards/assets/pic.png
Ayla/cards/assets/transparent_mask.png
Ayla/cards/card.py
Ayla/errors/__init__.py
Ayla/scrobbles/__init__.py
ayla-1.0.4.dist-info/LICENSE
ayla-1.0.4.dist-info/METADATA
ayla-1.0.4.dist-info/WHEEL
ayla-1.0.4.dist-info/RECORD
